devp2p/__init__.py
devp2p/app.py
devp2p/app_helper.py
devp2p/crypto.py
devp2p/discovery.py
devp2p/jsonrpc.py
devp2p/kademlia.py
devp2p/multiplexer.py
devp2p/muxsession.py
devp2p/p2p_protocol.py
devp2p/peer.py
devp2p/peermanager.py
devp2p/protocol.py
devp2p/rlpxcipher.py
devp2p/service.py
devp2p/slogging.py
devp2p/utils.py
devp2p/examples/__init__.py
devp2p/examples/full_app.py
devp2p/tests/__init__.py
devp2p/tests/test_crypto.py
devp2p/tests/test_discovery.py
devp2p/tests/test_ecies.py
devp2p/tests/test_full_app.py
devp2p/tests/test_go_handshake.py
devp2p/tests/test_go_signature.py
devp2p/tests/test_kademlia.py
devp2p/tests/test_kademlia_protocol.py
devp2p/tests/test_multiplexer.py
devp2p/tests/test_muxsession.py
devp2p/tests/test_p2pprotocol.py
devp2p/tests/test_peer.py
devp2p/tests/test_peermanager.py
devp2p/tests/test_rlpxsession.py
devp2p/tests/test_service.py
devp2p/tests/test_slogging.py
devp2p-0.9.2.dist-info/top_level.txt
devp2p-0.9.2.dist-info/METADATA
devp2p-0.9.2.dist-info/DESCRIPTION.rst
devp2p-0.9.2.dist-info/metadata.json
devp2p-0.9.2.dist-info/WHEEL
devp2p-0.9.2.dist-info/RECORD
