Metadata-Version: 2.0
Name: devp2p
Version: 0.9.2
Summary: Python implementation of the Ethereum P2P stack
Home-page: https://github.com/ethereum/pydevp2p
Author: HeikoHeiko
Author-email: heiko@ethdev.com
License: MIT
Keywords: devp2p
Platform: UNKNOWN
Classifier: Development Status :: 2 - Pre-Alpha
Classifier: Intended Audience :: Developers
Classifier: License :: OSI Approved :: MIT License
Classifier: Natural Language :: English
Classifier: Programming Language :: Python :: 2
Classifier: Programming Language :: Python :: 2.7
Classifier: Programming Language :: Python :: 3
Classifier: Programming Language :: Python :: 3.3
Classifier: Programming Language :: Python :: 3.4
Requires-Dist: wheel
Requires-Dist: tox
Requires-Dist: rlp (>=0.5.1,<0.6.0)
Requires-Dist: bitcoin
Requires-Dist: pycryptodome (>=3.3.1)
Requires-Dist: gevent (>=1.1.0)
Requires-Dist: pyelliptic
Requires-Dist: coverage
Requires-Dist: tinyrpc
Requires-Dist: ipaddress
Requires-Dist: secp256k1 (==0.13.2)
